{"network_id": "354c647e-5521-11e7-8f50-0ac135e8bacf", "ndex": "http://www.ndexbio.org", "e_set": "cravat_nci", "name": "Validated transcriptional targets of AP1 family members Fra1 and Fra2", "ids": ["LIF", "ATF4", "TXLNG", "CCNA2", "DMTF1", "NFATC3", "BGLAP", "USF2", "FOSL1", "NOS3", "SP1", "COL1A2", "MMP1", "ITGB4", "IVL", "THBD", "JUN", "MMP9", "CCND1", "EP300", "NFATC2", "GJA1", "DCN", "JUNB", "IL6", "HMOX1", "MMP2", "CDKN2A", "FOSL2", "PLAUR", "MGP", "CXCL8", "CCL2", "NFATC1", "LAMA3", "JUND", "PLAU"]}