{"network_id": "9697501e-5521-11e7-8f50-0ac135e8bacf", "ndex": "http://www.ndexbio.org", "e_set": "cravat_nci", "name": "Integrins in angiogenesis", "ids": ["GCH1", "COL6A1", "COL4A1", "SPP1", "ITGAV", "CASP8", "CBL", "CSF1R", "TGFBR2", "SDC1", "COL4A5", "MAPK3", "PIK3R1", "ILK", "SRC", "ITGB3", "EDIL3", "COL5A2", "IGF1R", "PTPN11", "RAC1", "HSP90AA1", "PXN", "CSF1", "FGF2", "ANGPTL3", "AKT1", "PTK2", "MFGE8", "TLN1", "PIK3CA", "COL11A2", "COL2A1", "COL4A4", "MAPK1", "COL6A6", "PI4KA", "COL4A6", "ADGRA2", "COL5A1", "PTK2B", "RPS6KB1", "COL6A3", "COL11A1", "COL7A1", "COL4A3", "KDR", "COL1A2", "VEGFA", "PI4KB", "IGF1", "VAV3", "IRS1", "ROCK1", "RHOA", "F11R", "COL6A5", "CDKN1B", "COL4A2", "PIK3C2A", "VCL", "COL1A1", "BCAR1", "FN1", "VTN", "COL3A1", "COL6A2"]}